rudderlabs/__init__.py
rudderlabs/data/__init__.py
rudderlabs/data/apps/__init__.py
rudderlabs/data/apps/config.py
rudderlabs/data/apps/constants.py
rudderlabs/data/apps/log.py
rudderlabs/data/apps/aws/__init__.py
rudderlabs/data/apps/aws/events.py
rudderlabs/data/apps/aws/lambda_utils.py
rudderlabs/data/apps/aws/processing.py
rudderlabs/data/apps/aws/s3.py
rudderlabs/data/apps/aws/session.py
rudderlabs/data/apps/scripts/__init__.py
rudderlabs/data/apps/scripts/aws.py
rudderlabs/data/apps/scripts/aws_ec2_instance.py
rudderlabs/data/apps/scripts/new.py
rudderlabs/data/apps/scripts/pipeline.py
rudderlabs/data/apps/scripts/rudderlabs.py
rudderlabs/data/apps/templates/.gitattributes
rudderlabs/data/apps/templates/.gitignore
rudderlabs/data/apps/templates/__init__.py
rudderlabs/data/apps/templates/project/.gitattributes
rudderlabs/data/apps/templates/project/.gitignore
rudderlabs/data/apps/templates/project/README.md
rudderlabs/data/apps/templates/project/__init__.py
rudderlabs/data/apps/templates/project/credentials_template.yaml
rudderlabs/data/apps/templates/project/data_loader.py
rudderlabs/data/apps/templates/project/model_loader.py
rudderlabs/data/apps/templates/project/requirements.txt
rudderlabs/data/apps/templates/project/run_notebook_wrapper.py
rudderlabs/data/apps/templates/project/conda/environment.yaml
rudderlabs/data/apps/templates/project/config/data_prep.yaml
rudderlabs/data/apps/templates/project/config/train.yaml
rudderlabs/data/apps/templates/project/config/train_automl.yaml
rudderlabs/data/apps/templates/project/config/validation.yaml
rudderlabs/data/apps/templates/project/data/.gitignore
rudderlabs/data/apps/templates/project/experimental/README.md
rudderlabs/data/apps/templates/project/experimental/train_pycaret_automl.ipynb
rudderlabs/data/apps/templates/project/experimental/img/mlflowUI001.png
rudderlabs/data/apps/templates/project/experimental/img/mlflowUI002.png
rudderlabs/data/apps/templates/project/notebooks/__init__.py
rudderlabs.data.apps-0.0.1b33.dist-info/LICENSE
rudderlabs.data.apps-0.0.1b33.dist-info/METADATA
rudderlabs.data.apps-0.0.1b33.dist-info/WHEEL
rudderlabs.data.apps-0.0.1b33.dist-info/entry_points.txt
rudderlabs.data.apps-0.0.1b33.dist-info/top_level.txt
rudderlabs.data.apps-0.0.1b33.dist-info/RECORD
