Metadata-Version: 2.1
Name: rudderlabs.data.apps
Version: 0.0.1b33
Summary: Rudderlabs data apps library
Home-page: https://github.com/rudderlabs1/rudderlabs.data.apps
Author: Srinivas
Author-email: cnu.1439@gmail.com
License: GPLv3
Keywords: rudderlabs
Classifier: License :: OSI Approved :: MIT License
Classifier: Natural Language :: English
Classifier: Programming Language :: Python
Classifier: Programming Language :: Python :: 3
Classifier: Topic :: Software Development :: Libraries :: Python Modules
License-File: LICENSE
Requires-Dist: setuptools
Requires-Dist: black >=19
Requires-Dist: click >=7
Requires-Dist: click-plugins
Requires-Dist: boto3
Requires-Dist: tqdm
Requires-Dist: requests
Requires-Dist: sphinx
Requires-Dist: termcolor
Requires-Dist: pre-commit
Requires-Dist: zipp
Requires-Dist: certifi
Requires-Dist: docformatter
Requires-Dist: pyyaml >=6.0
Requires-Dist: python-dateutil
Requires-Dist: twine <3
Requires-Dist: lxml
Requires-Dist: jinja2
Requires-Dist: tabulate
Requires-Dist: psutil
Requires-Dist: pytz
Requires-Dist: sagemaker
Requires-Dist: jupyter
Requires-Dist: pandas >=1.3.5
Requires-Dist: papermill
Requires-Dist: sqlalchemy-redshift
Requires-Dist: snowflake-sqlalchemy
Requires-Dist: sphinx-rtd-theme
Requires-Dist: pandas-redshift
Requires-Dist: scikit-learn
